django_stuff/__init__.py
django_stuff/fields.py
django_stuff/forms.py
django_stuff/logging_tools.py
django_stuff/validators.py
django_stuff/version.py
django_stuff/backends/__init__.py
django_stuff/backends/auth.py
django_stuff/models/__init__.py
django_stuff/models/exceptions.py
django_stuff/models/generic.py
django_stuff/models/history.py
django_stuff/models/managers.py
django_stuff/models/signals.py
django_stuff/utils/__init__.py
django_stuff/utils/generators.py
django_stuff/utils/generic.py
django_stuff/utils/string.py
django_stuff-0.7.2.dist-info/LICENSE
django_stuff-0.7.2.dist-info/METADATA
django_stuff-0.7.2.dist-info/WHEEL
django_stuff-0.7.2.dist-info/top_level.txt
django_stuff-0.7.2.dist-info/RECORD
