Metadata-Version: 2.1
Name: django-stuff
Version: 0.7.2
Summary: Library with common code for Django
Home-page: https://github.com/rhenter/django-stuff
Author: Rafael Henter
Author-email: rafael@henter.com.br
License: MIT
Keywords: utils tools django
Platform: UNKNOWN
Classifier: Development Status :: 4 - Beta
Classifier: Framework :: Django
Classifier: Intended Audience :: Developers
Classifier: License :: OSI Approved :: MIT License
Classifier: Programming Language :: Python :: 3
Classifier: Programming Language :: Python :: 3.4
Classifier: Programming Language :: Python :: 3.5
Classifier: Programming Language :: Python :: 3.6
Classifier: Programming Language :: Python :: 3.7
Classifier: Topic :: Software Development :: Libraries
Requires-Dist: cached-property (>=1.3.0)
Requires-Dist: django (>=1.11)
Requires-Dist: djangorestframework (>=3.7)
Requires-Dist: unipath
